word_tools/__init__.py
word_tools/generic_provider.py
word_tools/lookup.py
word_tools/lookup_provider.py
word_tools/merriam_provider.py
word_tools/object_factory.py
word_tools/stoopid_provider.py
word_tools/transform.py
word_tools/transform_provider.py
word_tools/urban_provider.py
word_tools/wiki_provider.py
word_tools/cli/__init__.py
word_tools/cli/cli.py
word_tools-0.2.0.dist-info/LICENSE
word_tools-0.2.0.dist-info/METADATA
word_tools-0.2.0.dist-info/WHEEL
word_tools-0.2.0.dist-info/entry_points.txt
word_tools-0.2.0.dist-info/top_level.txt
word_tools-0.2.0.dist-info/RECORD
